trkr/__init__.py
trkr/run.py
trkr/setup.py
trkr-0.4.5.dist-info/DESCRIPTION.rst
trkr-0.4.5.dist-info/METADATA
trkr-0.4.5.dist-info/RECORD
trkr-0.4.5.dist-info/WHEEL
trkr-0.4.5.dist-info/entry_points.txt
trkr-0.4.5.dist-info/metadata.json
trkr-0.4.5.dist-info/top_level.txt
